{"version":"0.4","title":"LP-CTA-BUTTON-19-dark-bg","type":"section","content":[{"id":"79300f35","settings":{"content_position":"middle","background_background":"gradient","background_color":"#00756d","background_color_b":"#004d5e","background_gradient_angle":{"unit":"deg","size":90},"padding":{"unit":"px","top":"100","right":"50","bottom":"100","left":"50","isLinked":false},"padding_tablet":{"unit":"px","top":"80","right":"30","bottom":"80","left":"30","isLinked":false},"padding_mobile":{"unit":"px","top":"50","right":"10","bottom":"50","left":"10","isLinked":false},"content_width":{"unit":"px","size":900},"heading_color":"#ffffff","color_text":"rgba(255,255,255,0.8)","color_link":"#00ba8e","color_link_hover":"#00af8c"},"elements":[{"id":"7433d369","settings":{"_column_size":100,"_inline_size":null,"content_position":"center","padding":{"unit":"px","top":"20","right":"20","bottom":"20","left":"20","isLinked":true},"padding_tablet":{"unit":"px","top":"10","right":"10","bottom":"10","left":"10","isLinked":true},"padding_mobile":{"unit":"px","top":"20","right":"10","bottom":"20","left":"10","isLinked":false}},"elements":[{"id":"4f604ab0","settings":{"title":"OPTIONAL SUBHEADING","align":"center","title_color":"#00ba8e","header_size":"p","typography_typography":"custom","typography_letter_spacing":{"unit":"px","size":0.5},"typography_letter_spacing_mobile":{"unit":"px","size":0.3}},"elements":[],"isInner":false,"widgetType":"heading","elType":"widget"},{"id":"53dac0a6","settings":{"title":"Use h2 or h3 heading","header_size":"h3","align":"center"},"elements":[],"isInner":false,"widgetType":"heading","elType":"widget"},{"id":"50baf662","settings":{"editor":"<p>I am text block. Click edit button to change this text. Lorem ipsum dolor sit amet, consectetur adipiscing elit. Ut elit tellus, luctus nec ullamcorper mattis.<\/p>","align":"center"},"elements":[],"isInner":false,"widgetType":"text-editor","elType":"widget"},{"id":"254b6c10","settings":{"structure":"20"},"elements":[{"id":"5c57f84b","settings":{"_column_size":50,"_inline_size":null},"elements":[{"id":"53bf85d1","settings":{"text":"Clickable Button ","align":"right","size":"lg","align_mobile":"justify","button_text_color":"#ffffff","background_color":"#00ba8e","hover_color":"#ffffff","button_background_hover_color":"#00af8c","border_radius":{"unit":"px","top":"35","right":"35","bottom":"35","left":"35","isLinked":true},"button_hover_border_color":"#00af8c","border_border":"solid","border_width":{"unit":"px","top":"2","right":"2","bottom":"2","left":"2","isLinked":true},"border_color":"#00ba8e"},"elements":[],"isInner":false,"widgetType":"button","elType":"widget"}],"isInner":true,"elType":"column"},{"id":"522fa75f","settings":{"_column_size":50,"_inline_size":null},"elements":[{"id":"2c66ff3d","settings":{"text":"Clickable Button","align":"left","size":"lg","align_mobile":"justify","button_text_color":"#ffffff","background_color":"rgba(255,255,255,0.01)","hover_color":"#ffffff","button_background_hover_color":"#00af8c","button_hover_border_color":"#00af8c","border_border":"solid","border_width":{"unit":"px","top":"2","right":"2","bottom":"2","left":"2","isLinked":true},"border_color":"#ffffff","border_radius":{"unit":"px","top":"35","right":"35","bottom":"35","left":"35","isLinked":true}},"elements":[],"isInner":false,"widgetType":"button","elType":"widget"}],"isInner":true,"elType":"column"}],"isInner":true,"elType":"section"}],"isInner":false,"elType":"column"}],"isInner":false,"elType":"section"}]}