{"version":"0.4","title":"LP-LOGOS-07-6logos-dark-bg","type":"section","content":[{"id":"690b161d","settings":{"background_background":"gradient","background_color":"#00756d","padding":{"unit":"px","top":"40","right":"50","bottom":"40","left":"50","isLinked":false},"padding_tablet":{"unit":"px","top":"30","right":"30","bottom":"30","left":"30","isLinked":false},"padding_mobile":{"unit":"px","top":"50","right":"10","bottom":"50","left":"10","isLinked":false},"background_gradient_angle":{"unit":"deg","size":90},"background_color_b":"#004d5e","heading_color":"#ffffff","color_text":"rgba(255,255,255,0.8)","color_link":"#00ba8e","color_link_hover":"#00af8c"},"elements":[{"id":"2940a465","settings":{"_column_size":100,"_inline_size":null,"padding":{"unit":"px","top":"0","right":"0","bottom":"0","left":"0","isLinked":true},"padding_tablet":{"unit":"px","top":"0","right":"0","bottom":"0","left":"0","isLinked":true}},"elements":[{"id":"78b2d5a3","settings":{"margin":{"unit":"px","top":"0","right":0,"bottom":"0","left":0,"isLinked":true},"content_width":{"unit":"px","size":900}},"elements":[{"id":"2373b08a","settings":{"_column_size":100,"_inline_size":null,"background_background":"classic","padding_mobile":{"unit":"px","top":"10","right":"10","bottom":"10","left":"10","isLinked":false},"content_position":"center"},"elements":[{"id":"b78dcf6","settings":{"title":"Featured On","header_size":"p","align":"center","title_color":"#00ba8e"},"elements":[],"isInner":false,"widgetType":"heading","elType":"widget"},{"id":"4ce4392b","settings":{"editor":"<p>Use white PNG images with transparent backgrounds.\u00a0Image width should be 300 pixels or less. You can adjust the image Opacity and Size using the Style tab. Remove this text widget when you're finished.<\/p>","align":"center"},"elements":[],"isInner":false,"widgetType":"text-editor","elType":"widget"}],"isInner":true,"elType":"column"}],"isInner":true,"elType":"section"},{"id":"6486353f","settings":{"structure":"30","margin":{"unit":"px","top":"0","right":0,"bottom":"0","left":0,"isLinked":true},"content_width":{"unit":"px","size":740}},"elements":[{"id":"2b99b329","settings":{"_column_size":33,"_inline_size":null,"background_background":"classic","padding":{"unit":"px","top":"20","right":"40","bottom":"20","left":"40","isLinked":false},"padding_tablet":{"unit":"px","top":"20","right":"30","bottom":"20","left":"30","isLinked":false},"padding_mobile":{"unit":"px","top":"10","right":"20","bottom":"10","left":"20","isLinked":false},"content_position":"center"},"elements":[{"id":"69da848a","settings":{"image":{"url":"https:\/\/www.divi01.com\/wp-content\/uploads\/logowhite.png","id":8721},"image_size":"medium","opacity":{"unit":"px","size":0.3}},"elements":[],"isInner":false,"widgetType":"image","elType":"widget"}],"isInner":true,"elType":"column"},{"id":"41411041","settings":{"_column_size":33,"_inline_size":null,"background_background":"classic","padding":{"unit":"px","top":"20","right":"40","bottom":"20","left":"40","isLinked":false},"padding_tablet":{"unit":"px","top":"20","right":"30","bottom":"20","left":"30","isLinked":false},"padding_mobile":{"unit":"px","top":"10","right":"20","bottom":"10","left":"20","isLinked":false},"content_position":"center"},"elements":[{"id":"61e65bba","settings":{"image":{"url":"https:\/\/www.divi01.com\/wp-content\/uploads\/logowhite.png","id":8721},"image_size":"medium","opacity":{"unit":"px","size":0.3}},"elements":[],"isInner":false,"widgetType":"image","elType":"widget"}],"isInner":true,"elType":"column"},{"id":"682fae1c","settings":{"_column_size":33,"_inline_size":null,"background_background":"classic","padding":{"unit":"px","top":"20","right":"40","bottom":"20","left":"40","isLinked":false},"padding_tablet":{"unit":"px","top":"20","right":"30","bottom":"20","left":"30","isLinked":false},"padding_mobile":{"unit":"px","top":"10","right":"20","bottom":"10","left":"20","isLinked":false},"content_position":"center"},"elements":[{"id":"439bc72","settings":{"image":{"url":"https:\/\/www.divi01.com\/wp-content\/uploads\/logowhite.png","id":8721},"image_size":"medium","opacity":{"unit":"px","size":0.3}},"elements":[],"isInner":false,"widgetType":"image","elType":"widget"}],"isInner":true,"elType":"column"}],"isInner":true,"elType":"section"},{"id":"55f1e3c9","settings":{"structure":"30","margin":{"unit":"px","top":"0","right":0,"bottom":"0","left":0,"isLinked":true},"content_width":{"unit":"px","size":740}},"elements":[{"id":"ca5e258","settings":{"_column_size":33,"_inline_size":null,"background_background":"classic","padding":{"unit":"px","top":"20","right":"40","bottom":"20","left":"40","isLinked":false},"padding_tablet":{"unit":"px","top":"20","right":"30","bottom":"20","left":"30","isLinked":false},"padding_mobile":{"unit":"px","top":"10","right":"20","bottom":"10","left":"20","isLinked":false},"content_position":"center"},"elements":[{"id":"7fb57d29","settings":{"image":{"url":"https:\/\/www.divi01.com\/wp-content\/uploads\/logowhite.png","id":8721},"image_size":"medium","opacity":{"unit":"px","size":0.3}},"elements":[],"isInner":false,"widgetType":"image","elType":"widget"}],"isInner":true,"elType":"column"},{"id":"3ac59ce3","settings":{"_column_size":33,"_inline_size":null,"background_background":"classic","padding":{"unit":"px","top":"20","right":"40","bottom":"20","left":"40","isLinked":false},"padding_tablet":{"unit":"px","top":"20","right":"30","bottom":"20","left":"30","isLinked":false},"padding_mobile":{"unit":"px","top":"10","right":"20","bottom":"10","left":"20","isLinked":false},"content_position":"center"},"elements":[{"id":"2cbdb296","settings":{"image":{"url":"https:\/\/www.divi01.com\/wp-content\/uploads\/logowhite.png","id":8721},"image_size":"medium","opacity":{"unit":"px","size":0.3}},"elements":[],"isInner":false,"widgetType":"image","elType":"widget"}],"isInner":true,"elType":"column"},{"id":"1b8038bd","settings":{"_column_size":33,"_inline_size":null,"background_background":"classic","padding":{"unit":"px","top":"20","right":"40","bottom":"20","left":"40","isLinked":false},"padding_tablet":{"unit":"px","top":"20","right":"30","bottom":"20","left":"30","isLinked":false},"padding_mobile":{"unit":"px","top":"10","right":"20","bottom":"10","left":"20","isLinked":false},"content_position":"center"},"elements":[{"id":"3c277c5d","settings":{"image":{"url":"https:\/\/www.divi01.com\/wp-content\/uploads\/logowhite.png","id":8721},"image_size":"medium","opacity":{"unit":"px","size":0.3}},"elements":[],"isInner":false,"widgetType":"image","elType":"widget"}],"isInner":true,"elType":"column"}],"isInner":true,"elType":"section"}],"isInner":false,"elType":"column"}],"isInner":false,"elType":"section"}]}