{"version":"0.4","title":"LP-TESTIMONIAL-04-dark-bg","type":"section","content":[{"id":"3c2ce874","settings":{"background_background":"gradient","background_color":"#00756d","padding":{"unit":"px","top":"100","right":"50","bottom":"100","left":"50","isLinked":false},"padding_tablet":{"unit":"px","top":"80","right":"30","bottom":"80","left":"30","isLinked":false},"padding_mobile":{"unit":"px","top":"50","right":"10","bottom":"50","left":"10","isLinked":false},"background_gradient_angle":{"unit":"deg","size":90},"background_color_b":"#004d5e","heading_color":"#ffffff","color_text":"rgba(255,255,255,0.8)","color_link":"#00ba8e","color_link_hover":"#00af8c"},"elements":[{"id":"5890a0a8","settings":{"_column_size":100,"_inline_size":null,"padding":{"unit":"px","top":"0","right":"0","bottom":"0","left":"0","isLinked":true},"padding_tablet":{"unit":"px","top":"0","right":"0","bottom":"0","left":"0","isLinked":true}},"elements":[{"id":"1e9d27e2","settings":{"margin":{"unit":"px","top":"0","right":0,"bottom":"0","left":0,"isLinked":true},"content_width":{"unit":"px","size":900}},"elements":[{"id":"5c338bdc","settings":{"_column_size":100,"_inline_size":null,"background_background":"classic","padding":{"unit":"px","top":"20","right":"20","bottom":"20","left":"20","isLinked":true},"padding_tablet":{"unit":"px","top":"10","right":"10","bottom":"10","left":"10","isLinked":true},"padding_mobile":{"unit":"px","top":"20","right":"10","bottom":"20","left":"10","isLinked":false},"content_position":"center","_inline_size_tablet":100},"elements":[{"id":"79634b41","settings":{"image":{"url":"https:\/\/www.divi01.com\/wp-content\/uploads\/woman-face-left-glasses-300.jpg","id":10226},"image_size":"thumbnail","image_border_radius":{"unit":"%","top":"50","right":"50","bottom":"50","left":"50","isLinked":true}},"elements":[],"isInner":false,"widgetType":"image","elType":"widget"},{"id":"3df43795","settings":{"image":{"url":"https:\/\/www.divi01.com\/wp-content\/uploads\/stars-150.png","id":13392},"image_size":"medium"},"elements":[],"isInner":false,"widgetType":"image","elType":"widget"},{"id":"1cb71521","settings":{"title":"\"The recommended photo size here is 300 x 300 pixels. Square photos will automatically appear as circles. I am text block. Click edit button to change this text.\"","header_size":"p","typography_typography":"custom","typography_font_size":{"unit":"em","size":1.7},"typography_font_size_tablet":{"unit":"em","size":1.6},"typography_font_size_mobile":{"unit":"em","size":1.5},"typography_line_height":{"unit":"em","size":1.4},"align":"center"},"elements":[],"isInner":false,"widgetType":"heading","elType":"widget"},{"id":"bdb47ea","settings":{"editor":"<p>- Emma, Company Name<\/p>","align":"center"},"elements":[],"isInner":false,"widgetType":"text-editor","elType":"widget"}],"isInner":true,"elType":"column"}],"isInner":true,"elType":"section"}],"isInner":false,"elType":"column"}],"isInner":false,"elType":"section"}]}